{"cameraMode":{"drawMode":0,"name":"Shaded","section":"Shading Mode"},"sceneLighting":true,"audioPlay":false,"sceneViewState":{"m_AlwaysRefresh":false,"showFog":true,"showSkybox":true,"showFlares":false,"showImageEffects":true,"showParticleSystems":true,"showVisualEffectGraphs":true,"m_FxEnabled":true},"in2DMode":false,"pivot":{"x":-770.1292724609375,"y":22.092994689941408,"z":269.1875305175781},"rotation":{"x":-0.05782254412770271,"y":0.22916825115680695,"z":-0.01348442118614912,"w":-0.9717592597007752},"size":1663.280517578125,"orthographic":true}